rnaseqmixture/__init__.py
rnaseqmixture/annotators.py
rnaseqmixture/correction.py
rnaseqmixture-0.1.0.dist-info/METADATA
rnaseqmixture-0.1.0.dist-info/WHEEL
rnaseqmixture-0.1.0.dist-info/top_level.txt
rnaseqmixture-0.1.0.dist-info/RECORD
