Metadata-Version: 2.1
Name: rnaseqmixture
Version: 0.1.0
Summary: rnaseq mixture correction
Home-page: http://www.imt.uni-marburg.de
Author: Florian Finkernagel
Author-email: finkernagel@imt.uni-marburg.de
License: UNKNOWN
Keywords: rnaseq TPM
Platform: UNKNOWN
Classifier: Programming Language :: Python
Classifier: Development Status :: 4 - Beta
Classifier: Environment :: Other Environment
Classifier: Intended Audience :: Developers
Classifier: License :: OSI Approved :: GNU Library or Lesser General Public License (LGPL)
Classifier: Operating System :: OS Independent
Classifier: Topic :: Software Development :: Libraries :: Python Modules
Requires-Dist: pandas
